{
  "0e93b819cc2e8121f7281dc8e4eaaf78" : {
    "statistic" : {
      "failed" : 0,
      "broken" : 0,
      "skipped" : 0,
      "passed" : 1,
      "unknown" : 0,
      "total" : 1
    },
    "items" : [ {
      "uid" : "6beee6d1a1f1e364",
      "reportUrl" : "https://gergo1001.github.io/selenium-py-peldatar/14//#testresult/6beee6d1a1f1e364",
      "status" : "passed",
      "time" : {
        "start" : 1624797440521,
        "stop" : 1624797440521,
        "duration" : 0
      }
    } ]
  },
  "753cdf21aa3257d3e2249d83346a13e6" : {
    "statistic" : {
      "failed" : 0,
      "broken" : 0,
      "skipped" : 0,
      "passed" : 1,
      "unknown" : 0,
      "total" : 1
    },
    "items" : [ {
      "uid" : "7dbd21abc5a10f4c",
      "reportUrl" : "https://gergo1001.github.io/selenium-py-peldatar/14//#testresult/7dbd21abc5a10f4c",
      "status" : "passed",
      "time" : {
        "start" : 1624797440520,
        "stop" : 1624797440520,
        "duration" : 0
      }
    } ]
  },
  "77caee529814bb5616db6b28df37c87c" : {
    "statistic" : {
      "failed" : 0,
      "broken" : 0,
      "skipped" : 0,
      "passed" : 1,
      "unknown" : 0,
      "total" : 1
    },
    "items" : [ {
      "uid" : "9620a51cb18b42da",
      "reportUrl" : "https://gergo1001.github.io/selenium-py-peldatar/14//#testresult/9620a51cb18b42da",
      "status" : "passed",
      "time" : {
        "start" : 1624797440518,
        "stop" : 1624797440519,
        "duration" : 1
      }
    } ]
  },
  "0cc1fa42e1c19a0d3fd610d45c4ba65a" : {
    "statistic" : {
      "failed" : 0,
      "broken" : 0,
      "skipped" : 0,
      "passed" : 1,
      "unknown" : 0,
      "total" : 1
    },
    "items" : [ {
      "uid" : "78a498919162bdd",
      "reportUrl" : "https://gergo1001.github.io/selenium-py-peldatar/14//#testresult/78a498919162bdd",
      "status" : "passed",
      "time" : {
        "start" : 1624797440516,
        "stop" : 1624797440516,
        "duration" : 0
      }
    } ]
  }
}